[{
    "fields": {
        "username": "admin",
        "first_name": "",
        "last_name": "",
        "is_active": true,
        "is_superuser": true,
        "is_staff": true,
        "last_login": "2015-09-07T08:36:22.814Z",
        "groups": [],
        "user_permissions": [],
        "password": "pbkdf2_sha256$20000$4sozFLsljJeo$NJ2vVZvZkJdGrSYMzZIqPCrvwMKlowhjb8YF3vm7XM0=",
        "email": "olufunmilade.oshodi@andela.com",
        "date_joined": "2015-09-03T09:01:00.053Z"
    },
    "model": "auth.user",
    "pk": 1
}, {
    "fields": {
        "user_id": 1,
        "place_of_work": "Andela NYC",
        "position": "ADMIN",
        "about": "Ninja",
        "github_username": "",
        "frequency": "weekly"
    },
    "model": "userprofile.userprofile",
    "pk": 1
}, {
    "fields": {
        "username": "lade",
        "first_name": "",
        "last_name": "",
        "is_active": true,
        "is_superuser": false,
        "is_staff": false,
        "last_login": "2015-09-07T14:47:15.882Z",
        "groups": [],
        "user_permissions": [],
        "password": "pbkdf2_sha256$20000$NkFpmmE2yg8C$iMWl1k047ZMfUkFb4xkdSsna/oUHvTxz7ILUewUQswc=",
        "email": "olufunmilade.oshodi@andela.com",
        "date_joined": "2015-09-03T22:06:57.468Z"
    },
    "model": "auth.user",
    "pk": 2
}, {
    "fields": {
        "user_id": 2,
        "place_of_work": "Andela Nigeria",
        "position": "Product Manager",
        "about": "Bad guy",
        "github_username": "",
        "frequency": "monthly"
    },
    "model": "userprofile.userprofile",
    "pk": 2
}, {
    "fields": {
        "username": "stan",
        "first_name": "",
        "last_name": "",
        "is_active": true,
        "is_superuser": true,
        "is_staff": true,
        "last_login": "2016-03-10T08:36:22.814Z",
        "groups": [],
        "user_permissions": [],
        "password": "pbkdf2_sha256$20000$eV2IGCXmA5vY$fJ9f2lZywnwyerMcqyQylF28EUVJQsVVKKy2uCxxr6Y=",
        "email": "stanley.ndagi@andela.com",
        "date_joined": "2015-09-03T09:01:00.053Z"
    },
    "model": "auth.user",
    "pk": 3
}, {
    "fields": {
        "user_id": 3,
        "place_of_work": "Andela Kenya",
        "position": "Class Three Nairobi Kenya",
        "about": "Wise guy",
        "github_username": "",
        "frequency": "daily"
    },
    "model": "userprofile.userprofile",
    "pk": 3
}, {
    "fields": {
        "username": "achile",
        "is_active": true,
        "is_superuser": true,
        "is_staff": true,
        "last_login": "2016-03-10T08:36:22.814Z",
        "groups": [],
        "user_permissions": [],
        "password": "pbkdf2_sha256$20000$eV2IGCXmA5vY$fJ9f2lZywnwyerMcqyQylF28EUVJQsVVKKy2uCxxr6Y=",
        "email": "achile@andela.com",
        "date_joined": "2015-09-03T09:01:00.053Z"
    },
    "model": "auth.user",
    "pk": 4
}, {
    "fields": {
        "user_id": 4,
        "place_of_work": "Andela",
        "position": "Class Thirteen Lagos Nigeria",
        "about": "Funny guy",
        "github_username": "",
        "frequency": "daily"
    },
    "model": "userprofile.userprofile",
    "pk": 4
}]